odoo8_addon_runbot_skip_tests-8.0.1.0.0-py2.7-nspkg.pth
odoo_addons/runbot_skip_tests/__openerp__.py
odoo_addons/runbot_skip_tests/runbot_build.py
odoo_addons/runbot_skip_tests/__init__.py
odoo8_addon_runbot_skip_tests-8.0.1.0.0.dist-info/top_level.txt
odoo8_addon_runbot_skip_tests-8.0.1.0.0.dist-info/WHEEL
odoo8_addon_runbot_skip_tests-8.0.1.0.0.dist-info/RECORD
odoo8_addon_runbot_skip_tests-8.0.1.0.0.dist-info/metadata.json
odoo8_addon_runbot_skip_tests-8.0.1.0.0.dist-info/DESCRIPTION.rst
odoo8_addon_runbot_skip_tests-8.0.1.0.0.dist-info/METADATA
odoo8_addon_runbot_skip_tests-8.0.1.0.0.dist-info/namespace_packages.txt
